l200geom/__init__.py
legend_pygeom_l200-0.8.1.dist-info/licenses/LICENSE
pygeoml200/__init__.py
pygeoml200/_version.py
pygeoml200/calibration.py
pygeoml200/cli.py
pygeoml200/core.py
pygeoml200/cryo.py
pygeoml200/fibers.py
pygeoml200/hpge_strings.py
pygeoml200/metadata.py
pygeoml200/top.py
pygeoml200/utils.py
pygeoml200/watertank.py
pygeoml200/wlsr.py
pygeoml200/configs/runtime_config_schema.yaml
pygeoml200/configs/dummy_geom/B99000A.json
pygeoml200/configs/dummy_geom/C99000A.json
pygeoml200/configs/dummy_geom/P99000A.json
pygeoml200/configs/dummy_geom/README.md
pygeoml200/configs/dummy_geom/V99000A.json
pygeoml200/configs/dummy_geom/channelmap.json
pygeoml200/configs/extra_meta/README.md
pygeoml200/configs/extra_meta/l200-p03-r%-T%-all-config.yaml
pygeoml200/configs/extra_meta/l200-p11-r%-T%-all-config.yaml
pygeoml200/configs/extra_meta/l200-p13-r%-T%-all-config.yaml
pygeoml200/configs/extra_meta/l200-p14-r%-T%-all-config.yaml
pygeoml200/configs/extra_meta/l200-p15-r%-T%-all-config.yaml
pygeoml200/configs/extra_meta/l200-p18-r%-T%-all-config.yaml
pygeoml200/configs/extra_meta/validity.yaml
pygeoml200/materials/__init__.py
pygeoml200/materials/ketek_sipm.py
pygeoml200/materials/surfaces.py
pygeoml200/models/BasePlate_large.stl
pygeoml200/models/BasePlate_medium.stl
pygeoml200/models/BasePlate_medium_ortec.stl
pygeoml200/models/BasePlate_small.stl
pygeoml200/models/BasePlate_xlarge.stl
pygeoml200/models/README.md
pygeoml200/models/StringSupportStructure-short.stl
pygeoml200/models/StringSupportStructure.stl
pygeoml200/models/TopPlate.stl
pygeoml200/models/TopPlate_ppc.stl
pygeoml200/models/TriStar_large.stl
pygeoml200/models/TriStar_medium.stl
pygeoml200/models/TriStar_small.stl
pygeoml200/models/TriStar_xlarge.stl
legend_pygeom_l200-0.8.1.dist-info/METADATA
legend_pygeom_l200-0.8.1.dist-info/WHEEL
legend_pygeom_l200-0.8.1.dist-info/entry_points.txt
legend_pygeom_l200-0.8.1.dist-info/top_level.txt
legend_pygeom_l200-0.8.1.dist-info/RECORD
