Metadata-Version: 2.4
Name: legend_pygeom_l200
Version: 0.8.1
Summary: Geometry model of the LEGEND-200 experimental setup
Author-email: Luigi Pertoldi <gipert@pm.me>
Maintainer: The LEGEND Collaboration
License-Expression: GPL-3.0
Project-URL: Homepage, https://github.com/legend-exp/legend-pygeom-l200
Project-URL: Bug Tracker, https://github.com/legend-exp/legend-pygeom-l200/issues
Project-URL: Discussions, https://github.com/legend-exp/legend-pygeom-l200/discussions
Project-URL: Changelog, https://github.com/legend-exp/legend-pygeom-l200/releases
Classifier: Intended Audience :: Developers
Classifier: Intended Audience :: Science/Research
Classifier: Operating System :: MacOS
Classifier: Operating System :: POSIX
Classifier: Operating System :: Unix
Classifier: Programming Language :: Python
Classifier: Programming Language :: Python :: 3
Classifier: Programming Language :: Python :: 3 :: Only
Classifier: Topic :: Scientific/Engineering
Requires-Python: >=3.10
License-File: LICENSE
Requires-Dist: dbetto
Requires-Dist: legend-pygeom-hpges>=0.9.0
Requires-Dist: legend-pygeom-optics>=0.15
Requires-Dist: legend-pygeom-tools>=0.1.0
Requires-Dist: numpy
Requires-Dist: pint
Requires-Dist: pyg4ometry>=1.3.4
Requires-Dist: pylegendmeta>=v1.3.1
Requires-Dist: pyyaml
Requires-Dist: scipy
Requires-Dist: jsonschema
Provides-Extra: all
Requires-Dist: legend-pygeom-l200[docs,test]; extra == "all"
Provides-Extra: docs
Requires-Dist: furo; extra == "docs"
Requires-Dist: myst-parser; extra == "docs"
Requires-Dist: sphinx; extra == "docs"
Requires-Dist: sphinx-copybutton; extra == "docs"
Requires-Dist: sphinx-subfigure; extra == "docs"
Provides-Extra: test
Requires-Dist: pre-commit; extra == "test"
Requires-Dist: pylegendtestdata; extra == "test"
Requires-Dist: pytest>=6.0; extra == "test"
Requires-Dist: pytest-cov; extra == "test"
Dynamic: license-file
